README.rst
pcd8544.py
setup.py
micropython_pcd8544.egg-info/PKG-INFO
micropython_pcd8544.egg-info/SOURCES.txt
micropython_pcd8544.egg-info/dependency_links.txt
micropython_pcd8544.egg-info/top_level.txt