Metadata-Version: 1.1
Name: micropython-pcd8544
Version: 1.1.0
Summary: MicroPython library for the PCD8544 LCD, used by Nokia 5110 displays.
Home-page: https://github.com/mcauser/micropython-pcd8544
Author: Mike Causer
Author-email: mcauser@gmail.com
License: MIT
Keywords: pcd8544 monochrome lcd nokia micropython
Platform: UNKNOWN
Classifier: Development Status :: 5 - Production/Stable
Classifier: Programming Language :: Python :: Implementation :: MicroPython
Classifier: License :: OSI Approved :: MIT License
